MANIFEST.in
README.md
setup.py
bin/cerndb_example
bin/get_passwd
bin/get_passwd_legacy
cerndb/config/__init__.py
cerndb/config/config.yaml
cerndb/getpasswd/__init__.py
cerndb/getpasswd/backends.py
cerndb/getpasswd/command_line.py
cerndb/log/__init__.py
cerndb/snow/__init__.py
cerndb_base.egg-info/PKG-INFO
cerndb_base.egg-info/SOURCES.txt
cerndb_base.egg-info/dependency_links.txt
cerndb_base.egg-info/not-zip-safe
cerndb_base.egg-info/requires.txt
cerndb_base.egg-info/top_level.txt
test/test_config.py
test/test_log.py